financejson/__about__.py
financejson/__init__.py
financejson/cli.py
financejson/convert.py
financejson/schema.json
financejson/tree.py
financejson/validate.py
financeJSON-1.0.1b8.dist-info/LICENCE
financeJSON-1.0.1b8.dist-info/METADATA
financeJSON-1.0.1b8.dist-info/WHEEL
financeJSON-1.0.1b8.dist-info/entry_points.txt
financeJSON-1.0.1b8.dist-info/top_level.txt
financeJSON-1.0.1b8.dist-info/RECORD
