Metadata-Version: 2.1
Name: financeJSON
Version: 1.0.1b8
Summary: A JSON based finance file format
Home-page: https://github.com/tomerten/financejson
Author: Tom Mertens
License: GNU General Public License v3.0
Platform: UNKNOWN
Classifier: Development Status :: 3 - Alpha
Classifier: Intended Audience :: Science/Research
Classifier: License :: OSI Approved :: GNU General Public License v3 (GPLv3)
Classifier: Programming Language :: Python :: 3.6
Classifier: Programming Language :: Python :: 3.7
Classifier: Programming Language :: Python :: 3.8
Classifier: Programming Language :: Python :: Implementation :: CPython
Classifier: Programming Language :: Python :: Implementation :: PyPy
Classifier: Topic :: Office/Business :: Financial
Classifier: Intended Audience :: Financial and Insurance Industry
Requires-Python: >=3.6
Requires-Dist: click (==7.0)
Requires-Dist: fastjsonschema (==2.14.1)
Requires-Dist: h5py (==2.10.0)
Requires-Dist: numexpr (==2.7.0)
Requires-Dist: numpy (==1.17.4)
Requires-Dist: pandas (==0.25.3)
Requires-Dist: python-dateutil (==2.8.1)
Requires-Dist: pytz (==2019.3)
Requires-Dist: six (==1.13.0)
Requires-Dist: tables (==3.6.1)
Requires-Dist: termcolor (==1.1.0)
Requires-Dist: xlrd (==1.2.0)
Requires-Dist: xlsxwriter (==1.2.6)
